devproject/__init__.py
devproject/celery.py
devproject/settings.py
devproject/test_settings.py
devproject/urls.py
devproject/wsgi.py
misago/__init__.py
misago/conftest.py
misago/test.py
misago/urls.py
misago/acl/__init__.py
misago/acl/admin.py
misago/acl/algebra.py
misago/acl/apps.py
misago/acl/buildacl.py
misago/acl/cache.py
misago/acl/context_processors.py
misago/acl/decorators.py
misago/acl/forms.py
misago/acl/middleware.py
misago/acl/models.py
misago/acl/objectacl.py
misago/acl/panels.py
misago/acl/providers.py
misago/acl/test.py
misago/acl/useracl.py
misago/acl/views.py
misago/acl/migrations/0001_initial.py
misago/acl/migrations/0002_acl_version_tracker.py
misago/acl/migrations/0003_default_roles.py
misago/acl/migrations/0004_cache_version.py
misago/acl/migrations/__init__.py
misago/acl/tests/__init__.py
misago/acl/tests/test_acl_algebra.py
misago/acl/tests/test_getting_user_acl.py
misago/acl/tests/test_mock_role_admin_form_data.py
misago/acl/tests/test_patching_user_acl.py
misago/acl/tests/test_providers.py
misago/acl/tests/test_roleadmin_views.py
misago/acl/tests/test_serializing_user_acl.py
misago/acl/tests/test_user_acl_context_processor.py
misago/acl/tests/test_user_acl_middleware.py
misago/admin/__init__.py
misago/admin/admin.py
misago/admin/apps.py
misago/admin/auth.py
misago/admin/discoverer.py
misago/admin/forms.py
misago/admin/hierarchy.py
misago/admin/middleware.py
misago/admin/test.py
misago/admin/urlpatterns.py
misago/admin/urls.py
misago/admin/templatetags/__init__.py
misago/admin/templatetags/misago_admin_form.py
misago/admin/tests/__init__.py
misago/admin/tests/test_404_view.py
misago/admin/tests/test_admin_form_templatetags.py
misago/admin/tests/test_admin_index_view.py
misago/admin/tests/test_admin_site_hierarchy.py
misago/admin/tests/test_admin_views_are_protected.py
misago/admin/tests/test_authorization.py
misago/admin/tests/test_generic_admin_list_view.py
misago/admin/tests/test_login_to_admin.py
steamers_misago-0.0.2.dist-info/LICENSE.rst
steamers_misago-0.0.2.dist-info/METADATA
steamers_misago-0.0.2.dist-info/WHEEL
steamers_misago-0.0.2.dist-info/top_level.txt
steamers_misago-0.0.2.dist-info/RECORD
