Metadata-Version: 2.1
Name: steamers-misago
Version: 0.0.2
Summary: Steamers-Misago is modern, fully featured forum application written in Python and ES6, powered by Django and React.js. It works out of the box and plays nicely with other projects like Django-CMS.
Home-page: https://github.com/Trievo/steamers-misago
Author: Mark Tripoli
Author-email: mark.tripoli@trievosoftware.com
License: GPLv2
Platform: UNKNOWN
Classifier: Development Status :: 4 - Beta
Classifier: Environment :: Web Environment
Classifier: Framework :: Django
Classifier: Intended Audience :: Developers
Classifier: Intended Audience :: System Administrators
Classifier: License :: OSI Approved :: GNU General Public License v2 (GPLv2)
Classifier: Operating System :: OS Independent
Classifier: Programming Language :: Python
Classifier: Programming Language :: Python :: 3.6
Classifier: Topic :: Internet :: WWW/HTTP
Classifier: Topic :: Internet :: WWW/HTTP :: Dynamic Content
Classifier: Topic :: Internet :: WWW/HTTP :: WSGI
Classifier: Topic :: Software Development :: Libraries :: Application Frameworks
Classifier: Topic :: Software Development :: Libraries :: Python Modules
Requires-Dist: amqp (==2.3.2)
Requires-Dist: atomicwrites (==1.2.1)
Requires-Dist: attrs (==18.2.0)
Requires-Dist: beautifulsoup4 (==4.6.3)
Requires-Dist: billiard (==3.5.0.5)
Requires-Dist: bleach (==2.1.4)
Requires-Dist: celery[redis] (==4.2.1)
Requires-Dist: certifi (==2018.8.24)
Requires-Dist: chardet (==3.0.4)
Requires-Dist: defusedxml (==0.5.0)
Requires-Dist: django-debug-toolbar (==1.8)
Requires-Dist: django-htmlmin (==0.10.0)
Requires-Dist: django-js-asset (==1.1.0)
Requires-Dist: django-mptt (==0.8.7)
Requires-Dist: django (==1.11.15)
Requires-Dist: djangorestframework (==3.6.4)
Requires-Dist: faker (==0.8.18)
Requires-Dist: html5lib (==0.999999999)
Requires-Dist: idna (==2.7)
Requires-Dist: kombu (==4.2.2.post1)
Requires-Dist: markdown (==2.6.11)
Requires-Dist: more-itertools (==5.0.0)
Requires-Dist: oauthlib (==2.1.0)
Requires-Dist: olefile (==0.45.1)
Requires-Dist: pillow (==4.1.1)
Requires-Dist: pluggy (==0.8.0)
Requires-Dist: psycopg2-binary (==2.7.5)
Requires-Dist: py (==1.7.0)
Requires-Dist: pyjwt (==1.6.4)
Requires-Dist: pytest-django (==3.4.4)
Requires-Dist: pytest-mock (==1.10.0)
Requires-Dist: pytest (==4.0.2)
Requires-Dist: python-dateutil (==2.7.3)
Requires-Dist: python3-openid (==3.1.0)
Requires-Dist: pytz (==2018.5)
Requires-Dist: redis (==2.10.6)
Requires-Dist: requests-oauthlib (==1.0.0)
Requires-Dist: requests (==2.20.0)
Requires-Dist: responses (==0.10.5)
Requires-Dist: six (==1.11.0)
Requires-Dist: snapshottest (==0.5.0)
Requires-Dist: social-auth-app-django (==3.1.0)
Requires-Dist: social-auth-core (==1.7.0)
Requires-Dist: sqlparse (==0.2.4)
Requires-Dist: termcolor (==1.1.0)
Requires-Dist: text-unidecode (==1.2)
Requires-Dist: unidecode (==0.4.21)
Requires-Dist: urllib3 (==1.23)
Requires-Dist: vine (==1.1.4)
Requires-Dist: webencodings (==0.5.1)
